<?xml version="1.0" encoding="UTF-8"?>
<beans xmlns="http://www.springframework.org/schema/beans"
	xmlns:xsi="http://www.w3.org/2001/XMLSchema-instance" xmlns:context="http://www.springframework.org/schema/context"
	xsi:schemaLocation="http://www.springframework.org/schema/beans http://www.springframework.org/schema/beans/spring-beans.xsd
		http://www.springframework.org/schema/context http://www.springframework.org/schema/context/spring-context.xsd">

	 <bean id="adminDao" class="hjjf.scss.dao.AdminDaoImpl">
		<property name="sessionFactory" ref="sessionFactory"></property>
	</bean>
	 <bean id="teacherDao" class="hjjf.scss.dao.TeacherDaoImpl">
		<property name="sessionFactory" ref="sessionFactory"></property>
	</bean>
	<bean id="studentDao" class="hjjf.scss.dao.StudentDaoImpl">
		<property name="sessionFactory" ref="sessionFactory"></property>
	</bean>
	
	<bean id="collegeDao" class="hjjf.scss.dao.CollegeDaoImpl">
		<property name="sessionFactory" ref="sessionFactory"></property>
	</bean>
	<bean id="departmentDao" class="hjjf.scss.dao.DepartmentDaoImpl">
		<property name="sessionFactory" ref="sessionFactory"></property>
	</bean>
	<bean id="professionDao" class="hjjf.scss.dao.ProfessionDaoImpl">
		<property name="sessionFactory" ref="sessionFactory"></property>
	</bean>
	<bean id="courseDao" class="hjjf.scss.dao.CourseDaoImpl">
		<property name="sessionFactory" ref="sessionFactory"></property>
	</bean>
	<bean id="classRoomDao" class="hjjf.scss.dao.ClassRoomDaoImpl">
		<property name="sessionFactory" ref="sessionFactory"></property>
	</bean>
	<bean id="classDao" class="hjjf.scss.dao.ClassDaoImpl">
		<property name="sessionFactory" ref="sessionFactory"></property>
	</bean>
	
	<bean id="teachtaskDao" class="hjjf.scss.dao.TeachTaskDaoImpl">
		<property name="sessionFactory" ref="sessionFactory"></property>
	</bean>
	
	<bean id="courseScheduleDao" class="hjjf.scss.dao.CourseScheduleDaoImpl">
		<property name="sessionFactory" ref="sessionFactory"></property>
	</bean>
	
	<bean id="scheduleDao" class="hjjf.scss.dao.ScheduleDaoImpl">
		<property name="sessionFactory" ref="sessionFactory"></property>
	</bean>
	
	<bean id="auditDao" class="hjjf.scss.dao.AuditDaoImpl">
		<property name="sessionFactory" ref="sessionFactory"></property>
	</bean>
	
	<bean id="noticeDao" class="hjjf.scss.dao.NoticeDaoImpl">
		<property name="sessionFactory" ref="sessionFactory"></property>
	</bean>
	
	
</beans>